{"0": {"XdistToGoal": 7.700000000000003, "YdistToGoal": 1.3999999999999986, "Head": 1, "LeftFoot": 0, "RightFoot": 0, "OtherBodyPart": 0, "YendLoc": 43.6, "ZendLoc": 3.3, "Goal": 0}, "1": {"XdistToGoal": 25.599999999999994, "YdistToGoal": 8.0, "Head": 0, "LeftFoot": 0, "RightFoot": 0, "OtherBodyPart": 1, "YendLoc": 42.5, "ZendLoc": 3.6, "Goal": 0}, "2": {"XdistToGoal": 17.900000000000006, "YdistToGoal": 7.700000000000003, "Head": 0, "LeftFoot": 0, "RightFoot": 0, "OtherBodyPart": 1, "YendLoc": 33.0, "ZendLoc": 5.4, "Goal": 0}, "3": {"XdistToGoal": 19.400000000000006, "YdistToGoal": 25.4, "Head": 0, "LeftFoot": 0, "RightFoot": 0, "OtherBodyPart": 1, "YendLoc": 60.7, "ZendLoc": 0.5, "Goal": 0}, "4": {"XdistToGoal": 15.0, "YdistToGoal": 16.4, "Head": 0, "LeftFoot": 0, "RightFoot": 0, "OtherBodyPart": 1, "YendLoc": 32.3, "ZendLoc": 0.1, "Goal": 0}, "5": {"XdistToGoal": 24.0, "YdistToGoal": 16.4, "Head": 0, "LeftFoot": 0, "RightFoot": 0, "OtherBodyPart": 1, "YendLoc": 24.7, "ZendLoc": 24.7, "Goal": 0}, "6": {"XdistToGoal": 21.299999999999997, "YdistToGoal": 7.299999999999997, "Head": 0, "LeftFoot": 0, "RightFoot": 0, "OtherBodyPart": 1, "YendLoc": 46.4, "ZendLoc": 46.4, "Goal": 0}, "7": {"XdistToGoal": 8.900000000000006, "YdistToGoal": 13.3, "Head": 0, "LeftFoot": 0, "RightFoot": 0, "OtherBodyPart": 1, "YendLoc": 31.3, "ZendLoc": 0.0, "Goal": 0}, "8": {"XdistToGoal": 23.900000000000006, "YdistToGoal": 18.0, "Head": 0, "LeftFoot": 0, "RightFoot": 0, "OtherBodyPart": 1, "YendLoc": 42.8, "ZendLoc": 3.0, "Goal": 0}, "9": {"XdistToGoal": 7.099999999999994, "YdistToGoal": 5.700000000000003, "Head": 1, "LeftFoot": 0, "RightFoot": 0, "OtherBodyPart": 0, "YendLoc": 43.9, "ZendLoc": 3.5, "Goal": 0}, "10": {"XdistToGoal": 31.700000000000003, "YdistToGoal": 7.799999999999997, "Head": 0, "LeftFoot": 0, "RightFoot": 0, "OtherBodyPart": 1, "YendLoc": 38.2, "ZendLoc": 0.1, "Goal": 0}, "11": {"XdistToGoal": 39.2, "YdistToGoal": 3.0, "Head": 0, "LeftFoot": 0, "RightFoot": 0, "OtherBodyPart": 1, "YendLoc": 36.1, "ZendLoc": 6.7, "Goal": 0}, "12": {"XdistToGoal": 8.299999999999997, "YdistToGoal": 1.7000000000000028, "Head": 1, "LeftFoot": 0, "RightFoot": 0, "OtherBodyPart": 0, "YendLoc": 23.3, "ZendLoc": 23.3, "Goal": 0}, "13": {"XdistToGoal": 29.200000000000003, "YdistToGoal": 13.100000000000001, "Head": 0, "LeftFoot": 0, "RightFoot": 0, "OtherBodyPart": 1, "YendLoc": 41.2, "ZendLoc": 0.5, "Goal": 0}, "14": {"XdistToGoal": 20.799999999999997, "YdistToGoal": 17.4, "Head": 0, "LeftFoot": 0, "RightFoot": 0, "OtherBodyPart": 1, "YendLoc": 48.5, "ZendLoc": 0.0, "Goal": 0}, "15": {"XdistToGoal": 2.200000000000003, "YdistToGoal": 10.299999999999997, "Head": 0, "LeftFoot": 0, "RightFoot": 0, "OtherBodyPart": 1, "YendLoc": 48.5, "ZendLoc": 0.0, "Goal": 0}, "16": {"XdistToGoal": 10.700000000000003, "YdistToGoal": 2.0, "Head": 0, "LeftFoot": 0, "RightFoot": 0, "OtherBodyPart": 1, "YendLoc": 37.8, "ZendLoc": 0.0, "Goal": 0}, "17": {"XdistToGoal": 26.200000000000003, "YdistToGoal": 15.3, "Head": 0, "LeftFoot": 0, "RightFoot": 0, "OtherBodyPart": 1, "YendLoc": 26.5, "ZendLoc": 26.5, "Goal": 0}, "18": {"XdistToGoal": 16.599999999999994, "YdistToGoal": 4.700000000000003, "Head": 0, "LeftFoot": 0, "RightFoot": 0, "OtherBodyPart": 1, "YendLoc": 33.6, "ZendLoc": 0.0, "Goal": 0}, "19": {"XdistToGoal": 2.799999999999997, "YdistToGoal": 13.200000000000003, "Head": 0, "LeftFoot": 0, "RightFoot": 0, "OtherBodyPart": 1, "YendLoc": 50.9, "ZendLoc": 50.9, "Goal": 0}, "20": {"XdistToGoal": 8.900000000000006, "YdistToGoal": 8.700000000000003, "Head": 0, "LeftFoot": 0, "RightFoot": 0, "OtherBodyPart": 1, "YendLoc": 41.6, "ZendLoc": 0.6, "Goal": 0}, "21": {"XdistToGoal": 36.599999999999994, "YdistToGoal": 18.4, "Head": 0, "LeftFoot": 0, "RightFoot": 0, "OtherBodyPart": 1, "YendLoc": 57.5, "ZendLoc": 57.5, "Goal": 0}, "22": {"XdistToGoal": 25.099999999999994, "YdistToGoal": 5.200000000000003, "Head": 0, "LeftFoot": 0, "RightFoot": 0, "OtherBodyPart": 1, "YendLoc": 44.5, "ZendLoc": 44.5, "Goal": 0}, "23": {"XdistToGoal": 16.799999999999997, "YdistToGoal": 18.4, "Head": 0, "LeftFoot": 0, "RightFoot": 0, "OtherBodyPart": 1, "YendLoc": 37.6, "ZendLoc": 3.8, "Goal": 0}, "24": {"XdistToGoal": 14.599999999999994, "YdistToGoal": 20.0, "Head": 0, "LeftFoot": 0, "RightFoot": 0, "OtherBodyPart": 1, "YendLoc": 47.2, "ZendLoc": 0.5, "Goal": 0}, "25": {"XdistToGoal": 5.299999999999997, "YdistToGoal": 17.4, "Head": 0, "LeftFoot": 0, "RightFoot": 0, "OtherBodyPart": 1, "YendLoc": 43.3, "ZendLoc": 0.3, "Goal": 0}}