{"0": {"XdistToGoal": 14.599999999999994, "YdistToGoal": 4.5, "Head": 1, "LeftFoot": 0, "RightFoot": 0, "OtherBodyPart": 0, "YendLoc": 39.1, "ZendLoc": 2.1, "Goal": 0}, "1": {"XdistToGoal": 7.599999999999994, "YdistToGoal": 0.6000000000000014, "Head": 1, "LeftFoot": 0, "RightFoot": 0, "OtherBodyPart": 0, "YendLoc": 48.3, "ZendLoc": 1.1, "Goal": 0}, "2": {"XdistToGoal": 7.799999999999997, "YdistToGoal": 7.899999999999999, "Head": 0, "LeftFoot": 0, "RightFoot": 0, "OtherBodyPart": 1, "YendLoc": 42.4, "ZendLoc": 0.9, "Goal": 0}, "3": {"XdistToGoal": 6.400000000000006, "YdistToGoal": 3.5, "Head": 0, "LeftFoot": 0, "RightFoot": 0, "OtherBodyPart": 1, "YendLoc": 38.0, "ZendLoc": 0.2, "Goal": 1}, "4": {"XdistToGoal": 19.099999999999994, "YdistToGoal": 12.600000000000001, "Head": 0, "LeftFoot": 0, "RightFoot": 0, "OtherBodyPart": 1, "YendLoc": 36.7, "ZendLoc": 36.7, "Goal": 0}, "5": {"XdistToGoal": 19.799999999999997, "YdistToGoal": 14.799999999999997, "Head": 0, "LeftFoot": 0, "RightFoot": 0, "OtherBodyPart": 1, "YendLoc": 45.2, "ZendLoc": 0.1, "Goal": 0}, "6": {"XdistToGoal": 13.599999999999994, "YdistToGoal": 8.399999999999999, "Head": 0, "LeftFoot": 0, "RightFoot": 0, "OtherBodyPart": 1, "YendLoc": 42.7, "ZendLoc": 0.5, "Goal": 1}, "7": {"XdistToGoal": 20.900000000000006, "YdistToGoal": 6.200000000000003, "Head": 0, "LeftFoot": 0, "RightFoot": 0, "OtherBodyPart": 1, "YendLoc": 36.7, "ZendLoc": 3.6, "Goal": 0}, "8": {"XdistToGoal": 15.099999999999994, "YdistToGoal": 11.5, "Head": 0, "LeftFoot": 0, "RightFoot": 0, "OtherBodyPart": 1, "YendLoc": 34.9, "ZendLoc": 0.2, "Goal": 0}, "9": {"XdistToGoal": 6.700000000000003, "YdistToGoal": 9.2, "Head": 0, "LeftFoot": 0, "RightFoot": 0, "OtherBodyPart": 1, "YendLoc": 39.7, "ZendLoc": 0.4, "Goal": 1}, "10": {"XdistToGoal": 4.900000000000006, "YdistToGoal": 10.200000000000003, "Head": 0, "LeftFoot": 0, "RightFoot": 0, "OtherBodyPart": 1, "YendLoc": 36.5, "ZendLoc": 0.8, "Goal": 1}, "11": {"XdistToGoal": 19.799999999999997, "YdistToGoal": 10.5, "Head": 0, "LeftFoot": 0, "RightFoot": 0, "OtherBodyPart": 1, "YendLoc": 41.9, "ZendLoc": 0.2, "Goal": 0}, "12": {"XdistToGoal": 3.5999999999999943, "YdistToGoal": 7.600000000000001, "Head": 0, "LeftFoot": 0, "RightFoot": 0, "OtherBodyPart": 1, "YendLoc": 36.2, "ZendLoc": 0.2, "Goal": 0}, "13": {"XdistToGoal": 11.900000000000006, "YdistToGoal": 0.29999999999999716, "Head": 0, "LeftFoot": 0, "RightFoot": 0, "OtherBodyPart": 1, "YendLoc": 43.5, "ZendLoc": 0.2, "Goal": 1}, "14": {"XdistToGoal": 26.5, "YdistToGoal": 20.4, "Head": 0, "LeftFoot": 0, "RightFoot": 0, "OtherBodyPart": 1, "YendLoc": 40.8, "ZendLoc": 1.7, "Goal": 0}, "15": {"XdistToGoal": 10.5, "YdistToGoal": 15.0, "Head": 0, "LeftFoot": 0, "RightFoot": 0, "OtherBodyPart": 1, "YendLoc": 26.1, "ZendLoc": 26.1, "Goal": 0}, "16": {"XdistToGoal": 19.900000000000006, "YdistToGoal": 10.100000000000001, "Head": 0, "LeftFoot": 0, "RightFoot": 0, "OtherBodyPart": 1, "YendLoc": 37.3, "ZendLoc": 0.2, "Goal": 0}, "17": {"XdistToGoal": 30.599999999999994, "YdistToGoal": 9.100000000000001, "Head": 0, "LeftFoot": 0, "RightFoot": 0, "OtherBodyPart": 1, "YendLoc": 37.6, "ZendLoc": 0.3, "Goal": 0}, "18": {"XdistToGoal": 30.0, "YdistToGoal": 7.799999999999997, "Head": 0, "LeftFoot": 0, "RightFoot": 0, "OtherBodyPart": 1, "YendLoc": 43.9, "ZendLoc": 0.2, "Goal": 0}}